grizzel/__init__.py
grizzel/cleaner.py
grizzel-0.1.3.dist-info/LICENSE.txt
grizzel-0.1.3.dist-info/METADATA
grizzel-0.1.3.dist-info/WHEEL
grizzel-0.1.3.dist-info/top_level.txt
grizzel-0.1.3.dist-info/RECORD
