Metadata-Version: 2.1
Name: grizzel
Version: 0.1.3
Summary: A simple text cleaning utility using NLTK and BeautifulSoup
Home-page: https://pypi.org/project/grizzel/
Author: Ratul Sur
Author-email: your@email.com
Classifier: Programming Language :: Python :: 3
Classifier: License :: OSI Approved :: MIT License
Classifier: Operating System :: OS Independent
Requires-Python: >=3.6
License-File: LICENSE.txt
Requires-Dist: nltk
Requires-Dist: beautifulsoup4
